setup.py
keras_sparsity_pattern/__init__.py
keras_sparsity_pattern.egg-info/PKG-INFO
keras_sparsity_pattern.egg-info/SOURCES.txt
keras_sparsity_pattern.egg-info/dependency_links.txt
keras_sparsity_pattern.egg-info/not-zip-safe
keras_sparsity_pattern.egg-info/requires.txt
keras_sparsity_pattern.egg-info/top_level.txt